kenny/__init__.py
kenny-0.0.2.dist-info/LICENSE
kenny-0.0.2.dist-info/METADATA
kenny-0.0.2.dist-info/WHEEL
kenny-0.0.2.dist-info/top_level.txt
kenny-0.0.2.dist-info/zip-safe
kenny-0.0.2.dist-info/RECORD
