Metadata-Version: 2.1
Name: kenny
Version: 0.0.2
Summary: kenny provides feature-rich clients to HTTP(s) APIs.
Home-page: https://github.com/rozelie/kenny
Author: Ryan Ozelie
Author-email: ryan.ozelie@gmail.com
License: MIT License
Keywords: requests,api,client,http,https
Classifier: Programming Language :: Python :: 3.9
Classifier: Programming Language :: Python :: 3.10
Classifier: Programming Language :: Python :: 3.11
Classifier: License :: OSI Approved :: MIT License
Classifier: Operating System :: OS Independent
License-File: LICENSE
Requires-Dist: requests (>=2.27.*)
Provides-Extra: dev
Requires-Dist: black (==22.12.0) ; extra == 'dev'
Requires-Dist: coverage-badge (==1.1.0) ; extra == 'dev'
Requires-Dist: mypy (==0.991) ; extra == 'dev'
Requires-Dist: ruff (==0.0.228) ; extra == 'dev'
Requires-Dist: pytest (==7.2.1) ; extra == 'dev'
Requires-Dist: pytest-cov (==4.0.0) ; extra == 'dev'
